{
            "uuid": "acbe4ddd-0a63-420d-8777-e50e76ac1104",
            "rule_type": "in",
            "rule_action": "ACCEPT",
            "rule_macro": null,
            "rule_source": null,
            "rule_dest": null,
            "rule_proto": "tcp",
            "rule_sport": 65535,
            "rule_dport": 65535,
            "rule_comment": "Test comment",
            "rule_status": 1,
            "rule_status_readable": "Enable",
            "created_at": "2023-06-15 07:06:57"
        }